gausstools/infertools_new/__init__.pyc
gausstools/infertools_new/__main__.pyc
gausstools/infertools_new/arguments.pyc
gausstools/infertools_new/boundary_filter.pyc
gausstools/infertools_new/cc.pyc
gausstools/infertools_new/cellpose_postprocess.pyc
gausstools/infertools_new/config.pyc
gausstools/infertools_new/convenience.pyc
gausstools/infertools_new/dataset.pyc
gausstools/infertools_new/ensure_model.pyc
gausstools/infertools_new/executor.pyc
gausstools/infertools_new/export.pyc
gausstools/infertools_new/histogram.pyc
gausstools/infertools_new/image.pyc
gausstools/infertools_new/infer.pyc
gausstools/infertools_new/numba_functions.cpython-310-x86_64-linux-gnu.so
gausstools/infertools_new/polygons_utils.pyc
gausstools/infertools_new/postprocess.pyc
gausstools/infertools_new/profiler.pyc
gausstools/infertools_new/stitching.pyc
gausstools/infertools_new/thread_executor.pyc
gausstools/infertools_new/transform.pyc
gausstools/infertools_new/utils.pyc
gausstools/infertools_new/version.pyc
gausstools/infertools_new/model/__init__.pyc
gausstools/infertools_new/model/_timed.pyc
gausstools/infertools_new/model/onnx_model.pyc
gausstools/infertools_new/model/torch_model.pyc
gausstools/infertools_new/model/cellpose/__init__.pyc
gausstools/infertools_new/model/cellpose/model.pyc
gausstools/infertools_new/model/cellpose/resnet_torch.pyc
turing_segment-0.3.9.dist-info/METADATA
turing_segment-0.3.9.dist-info/WHEEL
turing_segment-0.3.9.dist-info/entry_points.txt
turing_segment-0.3.9.dist-info/top_level.txt
turing_segment-0.3.9.dist-info/RECORD
turing_segment-0.3.9.dist-info/licenses/licenses/LICENSE
turing_segment-0.3.9.dist-info/licenses/licenses/NOTICE
turing_segment-0.3.9.dist-info/licenses/licenses/cellpose
turing_segment-0.3.9.dist-info/licenses/licenses/numba
turing_segment-0.3.9.dist-info/licenses/licenses/numpy
