Metadata-Version: 2.4
Name: turing_segment
Version: 0.3.9
Summary: BioTuring cell segmentation inference framework
Author: BioTuring
License: **Proprietary Software License Agreement**
License-File: licenses/LICENSE
License-File: licenses/NOTICE
License-File: licenses/cellpose
License-File: licenses/numba
License-File: licenses/numpy
Requires-Dist: torch>=2
Requires-Dist: shapely
Requires-Dist: onnx
Requires-Dist: onnxruntime-gpu
Requires-Dist: tifffile
Requires-Dist: numpy<2
Requires-Dist: scipy
Requires-Dist: zarr
Requires-Dist: tqdm
Requires-Dist: pandas
Requires-Dist: geopandas>=1
Requires-Dist: opencv-python
Requires-Dist: numba
Requires-Dist: pyarrow
Requires-Dist: imagecodecs
Requires-Dist: requests
Requires-Dist: pyyaml
Requires-Dist: nvidia-ml-py
Requires-Dist: joblib
Requires-Dist: scikit-image
Provides-Extra: dev
Requires-Dist: black; extra == "dev"
Requires-Dist: pytest; extra == "dev"
Requires-Dist: build; extra == "dev"
Requires-Dist: cellpose; extra == "dev"
Requires-Dist: pytest-cov; extra == "dev"
Dynamic: license-file
